calculator_papartynas/__init__.py
calculator_papartynas/calculator.py
calculator_papartynas-1.dist-info/LICENSE
calculator_papartynas-1.dist-info/WHEEL
calculator_papartynas-1.dist-info/METADATA
calculator_papartynas-1.dist-info/RECORD
