Metadata-Version: 2.1
Name: calculator-papartynas
Version: 1
Summary: Simple calculator module, supporting addition, subtraction, multiplication, division and taking nth root. 
Author-email: Martynas Petkevičius <mpetkevicius@gmail.com>
Requires-Python: >=3.11
Classifier: License :: OSI Approved :: GNU General Public License v3 or later (GPLv3+)
Project-URL: Home, https://github.com/TuringCollegeSubmissions/mapetke-DWWP.1.5
